comptox_analysis/__init__.py
comptox_analysis/App_domain/Applicability_domain.py
comptox_analysis/App_domain/__init__.py
comptox_analysis/ML_stacking/Combiner.py
comptox_analysis/ML_stacking/__init__.py
comptox_analysis/highlighting/__init__.py
comptox_analysis/highlighting/highlighting_atoms.py
comptox_analysis/visualizing/__init__.py
comptox_analysis/visualizing/predictable_tsne.py
comptox_analysis/visualizing/visualizing.py
comptox_analysis-1.0.dist-info/LICENSE
comptox_analysis-1.0.dist-info/METADATA
comptox_analysis-1.0.dist-info/WHEEL
comptox_analysis-1.0.dist-info/top_level.txt
comptox_analysis-1.0.dist-info/RECORD
