Metadata-Version: 2.1
Name: comptox_analysis
Version: 1.0
Summary: ML analysis
Home-page: https://github.com/PARODBE/comptox_analysis
Download-URL: https://github.com/PARODBE/comptox_analysis
Author: Pablo Rodríguez Belenguer
Author-email: parodbe@gmail.com
License: GNU
License-File: LICENSE
